certbot_dns_ionos/__init__.py
certbot_dns_ionos/dns_ionos.py
certbot_dns_ionos/dns_ionos_test.py
certbot_dns_ionos-2024.11.9.dist-info/LICENSE.txt
certbot_dns_ionos-2024.11.9.dist-info/METADATA
certbot_dns_ionos-2024.11.9.dist-info/WHEEL
certbot_dns_ionos-2024.11.9.dist-info/entry_points.txt
certbot_dns_ionos-2024.11.9.dist-info/top_level.txt
certbot_dns_ionos-2024.11.9.dist-info/RECORD
