Metadata-Version: 2.1
Name: certbot-dns-ionos
Version: 2024.11.9
Summary: IONOS DNS Authenticator plugin for Certbot
Home-page: https://github.com/helgeerbe/certbot-dns-ionos
Author: Helge Erbe
Author-email: helge@erbehome.de
License: Apache License 2.0
Classifier: Development Status :: 5 - Production/Stable
Classifier: Environment :: Plugins
Classifier: Intended Audience :: System Administrators
Classifier: License :: OSI Approved :: Apache Software License
Classifier: Operating System :: POSIX :: Linux
Classifier: Programming Language :: Python
Classifier: Programming Language :: Python :: 3
Classifier: Programming Language :: Python :: 3.8
Classifier: Programming Language :: Python :: 3.9
Classifier: Programming Language :: Python :: 3.10
Classifier: Programming Language :: Python :: 3.11
Classifier: Programming Language :: Python :: 3.12
Classifier: Topic :: Internet :: WWW/HTTP
Classifier: Topic :: Security
Classifier: Topic :: System :: Installation/Setup
Classifier: Topic :: System :: Networking
Classifier: Topic :: System :: Systems Administration
Classifier: Topic :: Utilities
Requires-Python: >=3.8
License-File: LICENSE.txt
Requires-Dist: acme >=3.0.0
Requires-Dist: certbot >=3.0.0
Requires-Dist: setuptools
Requires-Dist: requests
Requires-Dist: mock
Requires-Dist: requests-mock
